[
  {
    "hoverText": "Camera minerilor",
    "roomDetails": "Fost spatiu de cinema si banca, camera a fost renovata prin a ii se scoate zidurile de piatra de 1m grosime",
    "photoAlbum": "roomsAlbum",
    "thumbnailImgUrl": "img/rooms/thumbnail/1.jpg",
    "fullSizeImgUrl": "img/rooms/fullSize/1.jpg"
  },
  {
    "hoverText": "Camera cartilor",
    "roomDetails": "Cazare la fklhsdlkjhsdjkdfn dcdf dlfj dlfdfl jhfgdjkgb;sfg d dlfgj;kdf;gkjf;dkfg",
    "photoAlbum": "roomsAlbum",
    "thumbnailImgUrl": "img/rooms/thumbnail/2.jpg",
    "fullSizeImgUrl": "img/rooms/fullSize/2.jpg"
  },
  {
    "hoverText": "Camera cartilor",
    "roomDetails": "Raluca are mere djkdfn dcdf dlfj dlfdfl jhfgdjkgb;sfg d dlfgj;kdf;gkjf;dkfg",
    "photoAlbum": "roomsAlbum",
    "thumbnailImgUrl": "img/rooms/thumbnail/3.jpg",
    "fullSizeImgUrl": "img/rooms/fullSize/3.jpg"
  },
  {
    "hoverText": "Camera cartilor",
    "roomDetails": "Raluca are mere djkdfn dcdf dlfj dlfdfl jhfgdjkgb;sfg d dlfgj;kdf;gkjf;dkfg",
    "photoAlbum": "roomsAlbum",
    "thumbnailImgUrl": "img/rooms/thumbnail/4.jpg",
    "fullSizeImgUrl": "img/rooms/fullSize/4.jpg"
  }
]
