[
  {
    "title": "test",
    "details": "test",
    "firstSectionTitleText": "test",
    "firstSectionIconFontAwesomeClass": "test",
    "secondSectionTitleText": "test",
    "secondSectionIconFontAwesomeClass": "test",
    "thirdSectionTitleText": "",
    "thirdSectionIconFontAwesomeClass": "",
    "seeAlsoSectionTitleText": "Vezi ?i",
    "seeAlsoIconFontAwesomeClass": "fa fa-coffee",
    "seeAlsoSectionTitleText": "Vezi ?i",
    "seeAlsoIconFontAwesomeClass": "fa fa-coffee",
    "destinationPageLink": "test",
    "backgroundImgUrl": "test"
  }
]