{
  "presentation": {
    "title": "Pagina Principală",
    "headlineText": "Încă te mai întrebi: 'De ce să vizitez Roșia Montană?'",
    "description": "pe acest site găsești cazare și trasee spre atracțiile turistice de aici",
    "metaDescription": "Un loc tradițional de cazare în centrul istoric din Roșia Montană - Munții Apuseni. Aici găsiți și trasee de drumetie si de bicicleta spre principalele atractii turistice.",
    "headlineImg": "img/homePage/presentation.jpg",
    "showPageHeadline": false,
    "url": {
      "link": "",
      "textOnMouseOver": "homepage",
      "openInNewTab": false
    }
  },
  "sections": [
    {
      "type": "advertise",
      "centralCarousel": {
        "timeInterval": "7000",
        "slides": [
          {
            "page": "/home"
          },
          {
            "page": "/activities/trails/weatherStation"
          },
          {
            "page": "/activities/trails/romanGalleries"
          },
          {
            "page": "/activities/trails/fourLakes"
          },
          {
            "page": "/activities/trails/geamana"
          },
          {
            "page": "/activities/trails/historicalCenter"
          },
          {
            "page": "/activities/trails/carnic"
          }
        ]
      }
    },
    {
      "type": "title",
      "text": "<i class='fa fa-bed'></i> Unde stau?",
      "sectionId": "accommodation",
      "addLinkInPageHeadline": false
    },
    {
      "type": "advertise",
      "carouselBoxes": [
        {
          "timeInterval": "10000",
          "page": "/accommodation/rooms"
        },
        {
          "timeInterval": "10000",
          "page": "/accommodation/camping"
        }
      ]
    },
    {
      "type": "advertise",
      "banner": {
        "page": "/accommodation/facilities"
      }
    },
    {
      "type": "title",
      "text": "<i class='fa fa-bicycle'></i> Ce fac acolo?",
      "addLinkInPageHeadline": false,
      "sectionId": "activities"
    },
    {
      "type": "advertise",
      "carouselBoxes": [
        {
          "timeInterval": "10000",
          "page": "/activities/hiking"
        },
        {
          "timeInterval": "10000",
          "page": "/activities/cycling"
        }
      ]
    },
    {
      "type": "advertise",
      "banner": {
        "page": "/activities/trails/topAttractions"
      }
    },
    {
      "type": "title",
      "text": "<i class='fa fa-calendar'></i> De neratat",
      "sectionId": "recommendations",
      "addLinkInPageHeadline": false
    },
    {
      "type": "advertise",
      "carouselBoxes": [
        {
          "timeInterval": "10000",
          "page": "/recommendations/festival"
        },
        {
          "timeInterval": "10000",
          "page": "/recommendations/marathon"
        },
        {
          "timeInterval": "10000",
          "page": "/recommendations/monumentsRestorations"
        },
        {
          "timeInterval": "10000",
          "page": "/recommendations/steamTrain"
        },
        {
          "timeInterval": "10000",
          "page": "/recommendations/daffodilMeadow"
        },
        {
          "timeInterval": "10000",
          "page": "/recommendations/firstMai"
        },
        {
          "timeInterval": "10000",
          "page": "/recommendations/scoutsOng"
        },
        {
          "timeInterval": "10000",
          "page": "/recommendations/souvenirShop"
        }
      ]
    }
  ]
}