[
  {
    "title": "Drumeții",
    "details": "Parcurge traseele prin care descoperi localitatea si atractiile ei. Posibilitate inchiriere ghid",
    "destinationPageLink": "location.href='/casaPetri/pages/hiking/hiking.html?lang=ro'",
    "carouselImages": [
      {
        "carouselImgUrl": "/casaPetri/img/homePage/activities/hiking/1.jpg"
      },
      {
        "carouselImgUrl": "/casaPetri/img/homePage/activities/hiking/2.jpg"
      },
      {
        "carouselImgUrl": "/casaPetri/img/homePage/activities/hiking/3.jpg"
      }
    ]
  },
  {
    "title": "Ciclism",
    "details": "Pedaleaza pe traseele de mountain bike propuse pentru toate nivelele de pregatire",
    "destinationPageLink": "location.href='pages/bicycle/page.html?lang=ro'",
    "carouselImages": [
      {
        "carouselImgUrl": "/casaPetri/img/homePage/activities/bike/1.jpg"
      },
      {
        "carouselImgUrl": "/casaPetri/img/homePage/activities/bike/2.jpg"
      },
      {
        "carouselImgUrl": "/casaPetri/img/homePage/activities/bike/3.jpg"
      }
    ]
  }
]
