{
  "presentation": {
    "title": "HomePage",
    "headline": "Roșia Montană - the oldest locality from Transylvania",
    "description": "Here you'll find accommodation and trails along the touristic attractions",
    "fullWidthImg": "img/homePage/presentation/fullWidthImg.jpg",
    "smallBoxImg": "img/homePage/presentation/smallBoxImg.jpg"
  },
  "url": {
    "link": "en/home",
    "textOnMouseOver": "homepage",
    "openInNewTab": false
  },
  "metaData": {
    "title": "Casa Petri Rosia Montana",
    "description": "Accommodation in an old miner's house from the historical center of Rosia Montana, up in the Transylvania's mountains. Discover the roman galleries, mining industry, mountains, lakes or the historical buildings from our area by the hiking or cycling trails from this website. Rent guides and bikes.",
    "displayOnShareImg": "img/homePage/presentation/displayOnShareImg.jpg"
  },
  "config": {
    "showPageHeadline": false
  },
  "sections": [
    {
      "type": "presentationOfOtherPages",
      "carousel": {
        "timeInterval": "7000",
        "slides": [
          {
            "page": "en/home"
          },
          {
            "page": "en/activities/trails/weatherStation"
          },
          {
            "page": "en/activities/trails/romanGalleries"
          },
          {
            "page": "en/activities/trails/fourLakes"
          },
          {
            "page": "en/activities/trails/geamana"
          },
          {
            "page": "en/activities/trails/historicalCenter"
          },
          {
            "page": "en/activities/trails/carnic"
          }
        ]
      }
    },
    {
      "type": "title",
      "text": "<i class='fa fa-bed'></i> Where to stay?",
      "sectionId": "accommodation",
      "addLinkInPageHeadline": false
    },
    {
      "type": "presentationOfOtherPages",
      "detailBoxes": [
        {
          "page": "en/accommodation/rooms"
        },
        {
          "page": "en/accommodation/camping"
        }
      ]
    },
    {
      "type": "presentationOfOtherPages",
      "banner": {
        "page": "en/accommodation/booksAndCosy"
      }
    },
    {
      "type": "title",
      "text": "<i class='fa fa-bicycle'></i> What to do there?",
      "addLinkInPageHeadline": false,
      "sectionId": "activities"
    },
    {
      "type": "presentationOfOtherPages",
      "detailBoxes": [
        {
          "page": "en/activities/hiking"
        },
        {
          "page": "en/activities/cycling"
        }
      ]
    },
    {
      "type": "presentationOfOtherPages",
      "banner": {
        "page": "en/activities/trails/topAttractions"
      }
    },
    {
      "type": "title",
      "text": "<i class='fa fa-calendar'></i> Do not miss",
      "sectionId": "recommendations",
      "addLinkInPageHeadline": false
    },
    {
      "type": "presentationOfOtherPages",
      "detailBoxes": [
        {
          "page": "en/recommendations/festival"
        },
        {
          "page": "en/recommendations/marathon"
        },
        {
          "page": "en/recommendations/monumentsRestorations"
        },
        {
          "page": "en/recommendations/steamTrain"
        },
        {
          "page": "en/recommendations/daffodilMeadow"
        },
        {
          "page": "en/recommendations/firstMai"
        },
        {
          "page": "en/recommendations/scoutsOng"
        },
        {
          "page": "en/recommendations/souvenirShop"
        }
      ]
    }
  ]
}