{
  "presentation": {
    "title": "Lety și Șulei",
    "headline": "Traseul spre masivele Lety și Șulei",
    "description": "Urcăm spre Galeria Văidoaia și Tăul Mare până pe masivele Lety și Șulei, apoi coborâm pe la tăurile Corna și Brazi. <i class='fa fa-male'> ~4h </i> | <i class='fa fa-bicycle'> ~3h </i>",
    "fullWidthImg": "img/activities/trails/letySulei/presentation/fullWidthImg.jpg",
    "smallBoxImg": "img/activities/trails/letySulei/presentation/smallBoxImg.jpg"
  },
  "url": {
    "link": "ro/activities/trails/letySulei",
    "textOnMouseOver": "Vezi traseul...",
    "openInNewTab": false
  },
  "metaData": {
    "title": "Lety și Șulei. Trasee drumeție, biciletă Roșia Montană",
    "description": "Urcăm spre Galeria Văidoaia și Tăul Mare până pe masivele Lety și Șulei, apoi coborâm pe la tăurile Corna și Brazi. Vezi traseul și descoperă și alte trasee de drumeție sau bicicletă din Roșia Montană. Rezervă cazare, biciclete, ghizi, campare.",
    "displayOnShareImg": "img/activities/trails/letySulei/presentation/displayOnShareImg.jpg"
  },
  "config": {
    "showPageHeadline": true
  },
  "sections": [
    {
      "type": "title",
      "text": "<i class='fa fa-map-signs'></i> Traseu",
      "sectionId": "details",
      "addLinkInPageHeadline": true
    },
    {
      "type": "articles",
      "specificArticles": [
        {
          "textContent": "Traseul ne va duce pe la galeria Văidoaia și Tăul Mare după care vom urca până pe masivul Lety și Șulei pentru a admira belvederea de aici. Coborâm apoi spre Tăul Cornei și prin zona 'brazi' pe la Tăul Brazi.",
          "iframe": {
            "src": "https://www.google.com/maps/embed/v1/directions?origin=place_id:ChIJQZ3JRuDMTkcRDGNwUKmDb8c&destination=place_id:ChIJQZ3JRuDMTkcRDGNwUKmDb8c&key=AIzaSyBXjVYPa0dfbDd8B_uKaa8XK2RoMiK1BJc&mode=walking&waypoints=place_id:ChIJf7dBe97MTkcRUOKwgwP6qHs|place_id:ChIJx7yc5t3MTkcRNltvBWKr5_c|place_id:ChIJN_7HbtvMTkcRR4t4DYjDseQ|place_id:ChIJx0kJ88LMTkcRlbYRRD21As0|place_id:ChIJTQYp_OnMTkcRddyHh_E1Xgs|place_id:ChIJnTJOLfDMTkcR6Bj-a0LHYdg|place_id:ChIJhQHoGebMTkcRLANMbf7_4TA|place_id:ChIJnXWJjujMTkcRql7gwjCkj6Q",
            "list": [
              {
                "textOnMouseOver": "lungime",
                "text": "<i class='fa fa-arrows-h'></i> ~10km"
              },
              {
                "textOnMouseOver": "durata pe jos",
                "text": "<i class='fa fa-male'></i> ~4h"
              },
              {
                "textOnMouseOver": "durata cu bicicleta",
                "text": "<i class='fa fa-bicycle'></i> ~3h"
              },
              {
                "textOnMouseOver": "dificultate",
                "text": "<i class='fa fa-line-chart'></i> mediu"
              },
              {
                "textOnMouseOver": "ar fi bine să ai",
                "text": "<i class='fa fa-check-square-o'></i> bocanci de munte, pelerină, apă"
              }
            ]
          }
        }
      ]
    },
    {
      "type": "articles",
      "commonArticles": [
        {
          "category": "guidesAndBikes",
          "ids": [
            {
              "id": "details"
            }
          ]
        }
      ]
    },
    {
      "type": "title",
      "text": "<i class='fa fa-star'></i> Atracții",
      "sectionId": "attractions",
      "addLinkInPageHeadline": true
    },
    {
      "type": "articles",
      "commonArticles": [
        {
          "category": "attractions",
          "ids": [
            {
              "id": "vaidoaiaGalleries"
            },
            {
              "id": "szekeyHouse"
            },
            {
              "id": "bigLake"
            },
            {
              "id": "letySulei"
            },
            {
              "id": "cornaLake"
            },
            {
              "id": "braziLake"
            },
            {
              "id": "sicilianStreet"
            }
          ]
        }
      ]
    },
    {
      "type": "title",
      "text": "<i class='fa fa-child'></i> Gata traseul? Îți recomandam și:",
      "sectionId": "nextTrail",
      "addLinkInPageHeadline": false
    },
    {
      "type": "presentationOfOtherPages",
      "banner": {
        "page": "ro/activities/trails/historicCenter"
      }
    },
    {
      "type": "title",
      "text": "<i class='fa fa-coffee'></i> Vezi și",
      "sectionId": "accommodation",
      "addLinkInPageHeadline": false
    },
    {
      "type": "presentationOfOtherPages",
      "detailBoxes": [
        {
          "page": "ro/accommodation/rooms"
        },
        {
          "page": "ro/accommodation/camping"
        },
        {
          "page": "ro/activities/hiking"
        },
        {
          "page": "ro/activities/cycling"
        }
      ]
    }
  ]
}
